streamlit_datagrid/__init__.py
streamlit_datagrid/frontend/build/asset-manifest.json
streamlit_datagrid/frontend/build/bootstrap.min.css
streamlit_datagrid/frontend/build/index.html
streamlit_datagrid/frontend/build/precache-manifest.7468769589af10c43aeb700cfd5787f9.js
streamlit_datagrid/frontend/build/service-worker.js
streamlit_datagrid/frontend/build/static/js/2.34d7e940.chunk.js
streamlit_datagrid/frontend/build/static/js/2.34d7e940.chunk.js.LICENSE.txt
streamlit_datagrid/frontend/build/static/js/2.34d7e940.chunk.js.map
streamlit_datagrid/frontend/build/static/js/main.4cc03732.chunk.js
streamlit_datagrid/frontend/build/static/js/main.4cc03732.chunk.js.map
streamlit_datagrid/frontend/build/static/js/runtime-main.44d30fc2.js
streamlit_datagrid/frontend/build/static/js/runtime-main.44d30fc2.js.map
streamlit_datagrid-0.0.1.dist-info/LICENSE
streamlit_datagrid-0.0.1.dist-info/METADATA
streamlit_datagrid-0.0.1.dist-info/WHEEL
streamlit_datagrid-0.0.1.dist-info/top_level.txt
streamlit_datagrid-0.0.1.dist-info/RECORD
