Metadata-Version: 2.1
Name: streamlit-datagrid
Version: 0.0.1
Summary: Scrollable data grid for listing items.
Home-page: https://github.com/victorC97/streamlit_datagrid
Author: victorC97
Author-email: victor.cour@telecomnancy.net
License: UNKNOWN
Platform: UNKNOWN
Requires-Python: >=3.6
Requires-Dist: streamlit (>=0.63)
